dataglass/__init__.py
dataglass/automation/__init__.py
dataglass/automation/auto_preprocessing.py
dataglass/pipeline/__init__.py
dataglass/pipeline/pipeline.py
dataglass/preprocessing/__init__.py
dataglass/preprocessing/duplicate_handling.py
dataglass/preprocessing/feature_encoding.py
dataglass/preprocessing/feature_scaling.py
dataglass/preprocessing/missing_handling.py
dataglass/preprocessing/outlier_handling.py
dataglass/preprocessing/type_conversion.py
dataglass-0.8.0.dist-info/licenses/LICENSE
dataglass-0.8.0.dist-info/METADATA
dataglass-0.8.0.dist-info/WHEEL
dataglass-0.8.0.dist-info/top_level.txt
dataglass-0.8.0.dist-info/RECORD
