Metadata-Version: 2.4
Name: dataglass
Version: 0.8.0
Summary: dataglass is a Python library for data preprocessing, exploratory data analysis (EDA), and machine learning. It includes modules for handling missing values, detecting and resolving duplicates, managing outliers, feature encoding, type conversion, scaling, and pipeline integration. With its latest update, dataglass introduces intelligent automation which dynamically adapting preprocessing steps based on dataset characteristics, minimizing manual configuration and accelerating your workf
Author: Saman Teymouri
Author-email: Saman Teymouri <saman.teymouri@gmail.com>
License: BSD-3-Clause
Project-URL: Homepage, https://github.com/samantim/dataglass
Project-URL: Documentation, https://github.com/samantim/dataglass/wiki
Project-URL: Source, https://github.com/samantim/dataglass
Project-URL: Issues, https://github.com/samantim/dataglass/issues
Keywords: data preprocessing,EDA,machine learning,data cleaning,feature engineering,pipeline,pandas,scikit-learn
Classifier: Development Status :: 4 - Beta
Classifier: Intended Audience :: Developers
Classifier: Intended Audience :: Science/Research
Classifier: Intended Audience :: Education
Classifier: Topic :: Scientific/Engineering
Classifier: Topic :: Scientific/Engineering :: Information Analysis
Classifier: Topic :: Software Development :: Libraries :: Python Modules
Classifier: Topic :: Software Development :: Pre-processors
Classifier: Topic :: Utilities
Classifier: Programming Language :: Python :: 3.10
Classifier: Programming Language :: Python :: 3.11
Classifier: Programming Language :: Python :: 3.12
Classifier: Programming Language :: Python :: 3.13
Classifier: Operating System :: OS Independent
Requires-Python: >=3.10
License-File: LICENSE
Requires-Dist: pandas>=1.5
Requires-Dist: numpy>=1.21
Requires-Dist: scikit-learn>=1.1
Requires-Dist: matplotlib>=3.5
Requires-Dist: rapidfuzz>=3.0
Requires-Dist: seaborn>=0.11
Requires-Dist: category_encoders>=2.5
Dynamic: author
Dynamic: license-file
Dynamic: requires-python
